[
  {
    "Title": "Archive One",
    "Description": "2 registrations",
    "Items": [
      {
        "Title": "Registration 12 june 2021",
        "Description": "3 documents",
        "Items": [
          {
            "Title": "Document 1",
            "Description": "subtitle document 1",
            "Icon": "FileDocument"
          },
          {
            "Title": "Document 2",
            "Description": "subtitle document 2",
            "Icon": "FileDocument"
          },
          {
            "Title": "Document 3",
            "Description": "subtitle document 3",
            "Icon": "FileDocument"
          }
        ]
      },
      {
        "Title": "Registration 16 agust 2021",
        "Description": "1 document",
        "Items": [
          {
            "Title": "Document 4",
            "Description": "subtitle document 4",
            "Icon": "FileDocument"
          }
        ]
      }
    ]
  },
  {
    "Title": "Archive Two",
    "Description": "1 registration",
    "Items": [
      {
        "Title": "Registration 12 july 2021",
        "Description": "1 documents",
        "Items": [
          {
            "Title": "Document 5",
            "Description": "subtitle document 5",
            "Icon": "FileDocument"
          },
          {
            "Title": "Document 6",
            "Description": "subtitle document 6",
            "Icon": "FileDocument"
          }
        ]
      }
    ]
  }
]